wp_version_checker.py
wp_version_checker-0.4.1.dist-info/DESCRIPTION.rst
wp_version_checker-0.4.1.dist-info/METADATA
wp_version_checker-0.4.1.dist-info/RECORD
wp_version_checker-0.4.1.dist-info/WHEEL
wp_version_checker-0.4.1.dist-info/entry_points.txt
wp_version_checker-0.4.1.dist-info/metadata.json
wp_version_checker-0.4.1.dist-info/top_level.txt
